pyshellrunner/__init__.py
tests/__init__.py
tests/test_output.py
tests/test_pyshell_with_values.py
tests/test_run.py
pyshellrunner_sorinaso-0.6.0.dist-info/LICENSE
pyshellrunner_sorinaso-0.6.0.dist-info/METADATA
pyshellrunner_sorinaso-0.6.0.dist-info/WHEEL
pyshellrunner_sorinaso-0.6.0.dist-info/top_level.txt
pyshellrunner_sorinaso-0.6.0.dist-info/RECORD
