Metadata-Version: 2.1
Name: pyshellrunner-sorinaso
Version: 0.6.0
Summary: Simple shell runner with colors and features
Home-page: https://github.com/sorinaso/pyshellrunner
Author: Alejandro Souto
Author-email: sorinaso@gmail.com
License: UNKNOWN
Platform: UNKNOWN
Classifier: Programming Language :: Python :: 3
Classifier: License :: OSI Approved :: MIT License
Classifier: Operating System :: OS Independent
Requires-Python: >=3.6
